README.md
repeat.py
setup.py
repeat.egg-info/PKG-INFO
repeat.egg-info/SOURCES.txt
repeat.egg-info/dependency_links.txt
repeat.egg-info/entry_points.txt
repeat.egg-info/requires.txt
repeat.egg-info/top_level.txt