Metadata-Version: 1.2
Name: repeat
Version: 0.1.3
Summary: Repeat command N times every S seconds.
Home-page: http://github.com/lqez/repeat
Author: Park, Hyunwoo
Author-email: ez.amiryo@gmail.com
Maintainer: Park, Hyunwoo
Maintainer-email: ez.amiryo@gmail.com
License: UNKNOWN
Platform: UNKNOWN
Classifier: Topic :: Terminals
Classifier: Topic :: Utilities
Classifier: Environment :: Console
Classifier: Development Status :: 3 - Alpha
Classifier: Intended Audience :: Developers
Classifier: Intended Audience :: System Administrators
Classifier: Programming Language :: Python
Classifier: Programming Language :: Python :: 2.7
Classifier: Programming Language :: Python :: 3.6
Classifier: License :: OSI Approved :: MIT License
